reaction_mechanizer/__init__.py
reaction_mechanizer/drawing/__init__.py
reaction_mechanizer/drawing/mechanism_reaction_visualizer.py
reaction_mechanizer/pathway/__init__.py
reaction_mechanizer/pathway/reaction.py
ReactionMechanizer-1.1.1.dist-info/LICENSE
ReactionMechanizer-1.1.1.dist-info/METADATA
ReactionMechanizer-1.1.1.dist-info/WHEEL
ReactionMechanizer-1.1.1.dist-info/top_level.txt
ReactionMechanizer-1.1.1.dist-info/RECORD
