Metadata-Version: 2.1
Name: ReactionMechanizer
Version: 1.1.1
Summary: Simulate reactions from proposed steps/mechanisms
Home-page: https://github.com/ArmaanAhmed22/ReactionMechanizer
Author: Armaan Ahmed
License: MIT
Project-URL: Bug Tracker, https://github.com/ArmaanAhmed22/ReactionMechanizer/issues
Platform: unix
Platform: linux
Platform: osx
Platform: cygwin
Platform: win32
Classifier: Programming Language :: Python :: 3
Classifier: Programming Language :: Python :: 3 :: Only
Classifier: Programming Language :: Python :: 3.8
Classifier: Programming Language :: Python :: 3.9
Classifier: Programming Language :: Python :: 3.10
Requires-Python: >=3.8
License-File: LICENSE
Requires-Dist: matplotlib (>=3.5)
Requires-Dist: numpy (>=1.21)
Requires-Dist: pandas (>=1.3)
Requires-Dist: seaborn (>=0.11)
Requires-Dist: scipy (>=1.7)
Provides-Extra: testing
Requires-Dist: pytest (>=7.1) ; extra == 'testing'
Requires-Dist: pytest-cov (>=3.0) ; extra == 'testing'
Requires-Dist: mypy (>=0.942) ; extra == 'testing'
Requires-Dist: flake8 (>=4.0) ; extra == 'testing'
Requires-Dist: tox (>=3.24) ; extra == 'testing'
